<?xml version="1.0" standalone="yes"?>
<!--Generated by SISProjectCreator Version 1.0 -->
<Msg>
    <Item>
        <Key>Scope</Key>
        <Value>SIS.BCI</Value>
    </Item>
    <Item>
        <Key>MessageType</Key>
        <Value>Reading</Value>
    </Item>
    <Item>
        <Key>Sender</Key>
        <Value>PrjRemote</Value>
    </Item>
    <Item>
        <Key>Receiver</Key>
        <Value>Uploader</Value>
    </Item>
	<Item>
        <Key>Purpose</Key>
        <Value>upload</Value>
    </Item>
	<Item>
        <Key>Type</Key>
        <Value>TestReading</Value>
    </Item>
    <Item>
        <Key>Value</Key>
        <Value>alongstring.......</Value>
    </Item>
	 <Item>
        <Key>datetime</Key>
        <Value>Today!!.......</Value>
    </Item>
</Msg>
